setup.cfg
setup.py
ParametricModeling/ParametricModeling.py
ParametricModeling/__init__.py
ParametricModeling.egg-info/PKG-INFO
ParametricModeling.egg-info/SOURCES.txt
ParametricModeling.egg-info/dependency_links.txt
ParametricModeling.egg-info/not-zip-safe
ParametricModeling.egg-info/requires.txt
ParametricModeling.egg-info/top_level.txt