Metadata-Version: 1.0
Name: ParametricModeling
Version: 0.1.9
Summary: An Sklearn interface around scipy.optimize.least_squares for parametric modeling
Home-page: http://github.com/shubhankar90/ParametricModeling
Author: Shubhankar Mitra
Author-email: shubhankar90@gmail.com
License: BSD 3 clause
Platform: UNKNOWN
